npyfile/__init__.py
npyfile/npyfile.py
npyfile-1.0.0.dist-info/LICENSE
npyfile-1.0.0.dist-info/METADATA
npyfile-1.0.0.dist-info/WHEEL
npyfile-1.0.0.dist-info/entry_points.txt
npyfile-1.0.0.dist-info/top_level.txt
npyfile-1.0.0.dist-info/RECORD
